pickme/__init__.py
pickme-0.0.2.dist-info/METADATA
pickme-0.0.2.dist-info/WHEEL
pickme-0.0.2.dist-info/top_level.txt
pickme-0.0.2.dist-info/RECORD
