Metadata-Version: 2.4
Name: pickme
Version: 0.0.2
Summary: Smart LLM router
Author: Tanmay Sachan
Author-email: tnmysachan@gmail.com
License: BSD-3-Clause
Classifier: Development Status :: 1 - Planning
Classifier: License :: OSI Approved :: BSD License
Classifier: Programming Language :: Python :: 3.11
Requires-Python: >=3.11
Dynamic: author
Dynamic: author-email
Dynamic: classifier
Dynamic: description
Dynamic: description-content-type
Dynamic: license
Dynamic: requires-python
Dynamic: summary
